{
  "annotations": {
    "changelogDate": "20260609235438"
  },
  "applications": ["knstore"],
  "dto": "mapstruct",
  "fields": [
    {
      "fieldName": "direccion",
      "fieldType": "String",
      "fieldValidateRules": ["required", "maxlength"],
      "fieldValidateRulesMaxlength": "100"
    },
    {
      "fieldName": "barrio",
      "fieldType": "String",
      "fieldValidateRules": ["maxlength"],
      "fieldValidateRulesMaxlength": "100"
    },
    {
      "fieldName": "localidad",
      "fieldType": "String",
      "fieldValidateRules": ["maxlength"],
      "fieldValidateRulesMaxlength": "100"
    },
    {
      "fieldName": "departamento",
      "fieldType": "String",
      "fieldValidateRules": ["required", "maxlength"],
      "fieldValidateRulesMaxlength": "100"
    },
    {
      "fieldName": "municipio",
      "fieldType": "String",
      "fieldValidateRules": ["required", "maxlength"],
      "fieldValidateRulesMaxlength": "100"
    },
    {
      "fieldName": "activo",
      "fieldType": "Boolean",
      "fieldValidateRules": ["required"]
    }
  ],
  "name": "Direccion",
  "pagination": "pagination",
  "relationships": [
    {
      "otherEntityName": "cuenta",
      "relationshipName": "cuenta",
      "relationshipSide": "left",
      "relationshipType": "many-to-one",
      "relationshipValidateRules": "required"
    },
    {
      "otherEntityName": "pedido",
      "otherEntityRelationshipName": "direccion",
      "relationshipName": "pedido",
      "relationshipSide": "right",
      "relationshipType": "one-to-one"
    }
  ],
  "searchEngine": "no",
  "service": "serviceImpl"
}
